{
    "LL-J38-Valencia-Barcelona": true,
    "LL-J37-Barcelona-RealBetis": true,
    "LL-J37-SevillaFC-RealMadrid": true,
    "LL-J36-Alaves-Barcelona": true,
    "LL-J35-Barcelona-RealMadrid": true,
    "LL-J01-Mallorca-Barcelona": true,
    "LL-J30-AtleticoMadrid-Barcelona": "https://www.rtve.es/drmn/embed/video/17008055",
    "LL-J30-Girona-Villarreal": "https://www.rtve.es/drmn/embed/video/17008477",
    "LL-J30-Alaves-Osasuna": "https://www.rtve.es/drmn/embed/video/17008448",
    "LL-J30-Oviedo-SevillaFC": "https://www.rtve.es/drmn/embed/video/17008446",
    "LL-J30-Valencia-CeltadeVigo": "https://www.rtve.es/drmn/embed/video/17008441",
    "LL-J30-Getafe-AthleticClub": "https://www.rtve.es/drmn/embed/video/17008438",
    "LL-J30-RealBetis-Espanyol": "https://www.rtve.es/drmn/embed/video/17008052",
    "LL-J30-Mallorca-RealMadrid": "https://www.rtve.es/drmn/embed/video/17008048",
    "LL-J30-RealSociedad-Levante": "https://www.rtve.es/drmn/embed/video/17008046",
    "LL-J30-RayoVallecano-Elche": "https://www.rtve.es/drmn/embed/video/17008045"
}
