{"venue":{"city":"Getafe","name":"Coliseum Alfonso Pérez","country":"Spain","capacity":"16500"},"referee":{"name":"Hernandez Hernandez, Alejandro Jose","nationality":"Spain"},"forecast":{"status":"partly cloudy night","temperature":"7.62°C"},"events":[{"team":{"id":465430,"logo":"https://highlightly.net/soccer/images/teams/465430.png","name":"Getafe"},"time":"43","type":"Yellow Card","assist":null,"player":"L. Milla","playerId":7580839,"substituted":null,"assistingPlayerId":null},{"team":{"id":679031,"logo":"https://highlightly.net/soccer/images/teams/679031.png","name":"Elche"},"time":"46","type":"Substitution","assist":null,"player":"G. Diangana","playerId":3030335,"substituted":"R. Mendoza","assistingPlayerId":54960885},{"team":{"id":465430,"logo":"https://highlightly.net/soccer/images/teams/465430.png","name":"Getafe"},"time":"56","type":"Goal","assist":"Kiko Femenia","player":"M. Arambarri","playerId":7608692,"substituted":null,"assistingPlayerId":3025988},{"team":{"id":679031,"logo":"https://highlightly.net/soccer/images/teams/679031.png","name":"Elche"},"time":"61","type":"Substitution","assist":null,"player":"M. Neto","playerId":43724534,"substituted":"M. Aguado","assistingPlayerId":30158352},{"team":{"id":679031,"logo":"https://highlightly.net/soccer/images/teams/679031.png","name":"Elche"},"time":"64","type":"Substitution","assist":null,"player":"H. Fort","playerId":62284453,"substituted":"A. Pedrosa","assistingPlayerId":7620123},{"team":{"id":465430,"logo":"https://highlightly.net/soccer/images/teams/465430.png","name":"Getafe"},"time":"65","type":"Substitution","assist":null,"player":"A. Nyom","playerId":7632681,"substituted":"D. Rico","assistingPlayerId":3037741},{"team":{"id":679031,"logo":"https://highlightly.net/soccer/images/teams/679031.png","name":"Elche"},"time":"72","type":"Substitution","assist":null,"player":"Andre Silva","playerId":332297,"substituted":"R. Mir","assistingPlayerId":7569247},{"team":{"id":679031,"logo":"https://highlightly.net/soccer/images/teams/679031.png","name":"Elche"},"time":"72","type":"Substitution","assist":null,"player":"G. Valera","playerId":26076197,"substituted":"Y. Santiago","assistingPlayerId":45790969},{"team":{"id":679031,"logo":"https://highlightly.net/soccer/images/teams/679031.png","name":"Elche"},"time":"73","type":"Yellow Card","assist":null,"player":"R. Mendoza","playerId":54960885,"substituted":null,"assistingPlayerId":null},{"team":{"id":465430,"logo":"https://highlightly.net/soccer/images/teams/465430.png","name":"Getafe"},"time":"78","type":"Yellow Card","assist":null,"player":"Djene","playerId":7607404,"substituted":null,"assistingPlayerId":null},{"team":{"id":465430,"logo":"https://highlightly.net/soccer/images/teams/465430.png","name":"Getafe"},"time":"80","type":"Substitution","assist":null,"player":"Alex Sancris","playerId":88043326,"substituted":"A. Kamara","assistingPlayerId":45795155},{"team":{"id":465430,"logo":"https://highlightly.net/soccer/images/teams/465430.png","name":"Getafe"},"time":"80","type":"Substitution","assist":null,"player":"Kiko Femenia","playerId":3025988,"substituted":"Javier Munoz","assistingPlayerId":7544614},{"team":{"id":679031,"logo":"https://highlightly.net/soccer/images/teams/679031.png","name":"Elche"},"time":"86","type":"Yellow Card","assist":null,"player":"M. Aguado","playerId":30158352,"substituted":null,"assistingPlayerId":null},{"team":{"id":465430,"logo":"https://highlightly.net/soccer/images/teams/465430.png","name":"Getafe"},"time":"90","type":"Substitution","assist":null,"player":"B. Mayoral","playerId":7643146,"substituted":"Y. Neyou","assistingPlayerId":6758290}],"predictions":{"live":[{"type":"live","modelType":"three-way","description":"Getafe is most likely to win the game against Elche.","generatedAt":"2025-11-28T20:00:47.753Z","probabilities":{"away":"25.35%","draw":"32.47%","home":"42.18%"}},{"type":"live","modelType":"three-way","description":"Getafe is most likely to win the game against Elche.","generatedAt":"2025-11-28T20:10:41.141Z","probabilities":{"away":"25.11%","draw":"32.61%","home":"42.28%"}},{"type":"live","modelType":"three-way","description":"Getafe is most likely to win the game against Elche.","generatedAt":"2025-11-28T20:21:05.051Z","probabilities":{"away":"24.09%","draw":"34.96%","home":"40.95%"}},{"type":"live","modelType":"three-way","description":"Getafe is most likely to win the game against Elche.","generatedAt":"2025-11-28T20:30:46.602Z","probabilities":{"away":"24.41%","draw":"37.67%","home":"37.91%"}},{"type":"live","modelType":"three-way","description":"The match will most likely result in a draw.","generatedAt":"2025-11-28T20:40:44.076Z","probabilities":{"away":"24.68%","draw":"40.68%","home":"34.64%"}},{"type":"live","modelType":"three-way","description":"The match will most likely result in a draw.","generatedAt":"2025-11-28T20:50:37.846Z","probabilities":{"away":"23.84%","draw":"43.35%","home":"32.81%"}},{"type":"live","modelType":"three-way","description":"The match will most likely result in a draw.","generatedAt":"2025-11-28T21:01:31.863Z","probabilities":{"away":"24.29%","draw":"43.65%","home":"32.06%"}},{"type":"live","modelType":"three-way","description":"The match will most likely result in a draw.","generatedAt":"2025-11-28T21:11:09.167Z","probabilities":{"away":"23.37%","draw":"45.21%","home":"31.41%"}},{"type":"live","modelType":"three-way","description":"Getafe is most likely to win the game against Elche.","generatedAt":"2025-11-28T21:21:16.117Z","probabilities":{"away":"3.92%","draw":"19.23%","home":"76.85%"}},{"type":"live","modelType":"three-way","description":"Getafe is most likely to win the game against Elche.","generatedAt":"2025-11-28T21:31:12.937Z","probabilities":{"away":"2.69%","draw":"17.37%","home":"79.93%"}},{"type":"live","modelType":"three-way","description":"Getafe is most likely to win the game against Elche.","generatedAt":"2025-11-28T21:41:42.834Z","probabilities":{"away":"1.72%","draw":"15.28%","home":"83.00%"}},{"type":"live","modelType":"three-way","description":"Getafe is most likely to win the game against Elche.","generatedAt":"2025-11-28T21:51:11.555Z","probabilities":{"away":"0.86%","draw":"9.77%","home":"89.36%"}}],"prematch":[{"type":"prematch","modelType":"three-way","description":"Getafe is most likely to win the game against Elche.","generatedAt":"2025-11-21T04:35:02.849Z","probabilities":{"away":"24.97%","draw":"32.40%","home":"42.63%"}},{"type":"prematch","modelType":"three-way","description":"Getafe is most likely to win the game against Elche.","generatedAt":"2025-11-22T04:32:37.540Z","probabilities":{"away":"24.95%","draw":"32.43%","home":"42.62%"}},{"type":"prematch","modelType":"three-way","description":"Getafe is most likely to win the game against Elche.","generatedAt":"2025-11-23T03:45:47.024Z","probabilities":{"away":"25.06%","draw":"32.36%","home":"42.58%"}},{"type":"prematch","modelType":"three-way","description":"Getafe is most likely to win the game against Elche.","generatedAt":"2025-11-24T02:57:52.819Z","probabilities":{"away":"25.06%","draw":"32.23%","home":"42.72%"}},{"type":"prematch","modelType":"three-way","description":"Getafe is most likely to win the game against Elche.","generatedAt":"2025-11-25T02:57:39.094Z","probabilities":{"away":"24.78%","draw":"32.15%","home":"43.06%"}},{"type":"prematch","modelType":"three-way","description":"Getafe is most likely to win the game against Elche.","generatedAt":"2025-11-26T02:55:53.298Z","probabilities":{"away":"24.92%","draw":"32.22%","home":"42.86%"}},{"type":"prematch","modelType":"three-way","description":"Getafe is most likely to win the game against Elche.","generatedAt":"2025-11-27T02:46:04.253Z","probabilities":{"away":"24.81%","draw":"32.31%","home":"42.88%"}},{"type":"prematch","modelType":"three-way","description":"Getafe is most likely to win the game against Elche.","generatedAt":"2025-11-28T02:36:19.479Z","probabilities":{"away":"24.65%","draw":"32.49%","home":"42.86%"}}]},"statistics":[{"team":{"id":465430,"logo":"https://highlightly.net/soccer/images/teams/465430.png","name":"Getafe"},"statistics":[{"value":1.06,"displayName":"Expected Goals"},{"value":1,"displayName":"Big Chances Created"},{"value":11,"displayName":"Free Kicks"},{"value":0.63,"displayName":"Expected Assists"},{"value":7,"displayName":"Successful Crosses"},{"value":20,"displayName":"Crosses"},{"value":75,"displayName":"Passes Own Half"},{"value":201,"displayName":"Passes Opposition Half"},{"value":22,"displayName":"Successful Long Passes"},{"value":47,"displayName":"Long Passes"},{"value":29,"displayName":"Throw-Ins"},{"value":8,"displayName":"Key Passes"},{"value":49,"displayName":"Passes Into Final Third"},{"value":39,"displayName":"Backward Passes"},{"value":6,"displayName":"Goal Kicks"},{"value":4,"displayName":"Interceptions"},{"value":8,"displayName":"Successful Tackles"},{"value":13,"displayName":"Tackles"},{"value":21,"displayName":"Clearances"},{"value":14,"displayName":"Successful Aerial Duels"},{"value":28,"displayName":"Aerial Duels"},{"value":4,"displayName":"Successful Dribbles"},{"value":8,"displayName":"Dribbles"},{"value":0.4,"displayName":"Shots accuracy"},{"value":79,"displayName":"Failed passes"},{"value":0.34,"displayName":"Possession"},{"value":6,"displayName":"Shots on target"},{"value":3,"displayName":"Corners"},{"value":2,"displayName":"Offsides"},{"value":177,"displayName":"Successful passes"},{"value":5,"displayName":"Shots off target"},{"value":4,"displayName":"Blocked shots"},{"value":8,"displayName":"Shots within penalty area"},{"value":256,"displayName":"Total passes"},{"value":7,"displayName":"Shots outside penalty area"},{"value":4,"displayName":"Goalkeeper saves"},{"value":18,"displayName":"Fouls"},{"value":2,"displayName":"Yellow cards"}]},{"team":{"id":679031,"logo":"https://highlightly.net/soccer/images/teams/679031.png","name":"Elche"},"statistics":[{"value":0.51,"displayName":"Expected Goals"},{"value":0,"displayName":"Big Chances Created"},{"value":17,"displayName":"Free Kicks"},{"value":0.79,"displayName":"Expected Assists"},{"value":6,"displayName":"Successful Crosses"},{"value":16,"displayName":"Crosses"},{"value":260,"displayName":"Passes Own Half"},{"value":288,"displayName":"Passes Opposition Half"},{"value":31,"displayName":"Successful Long Passes"},{"value":59,"displayName":"Long Passes"},{"value":22,"displayName":"Throw-Ins"},{"value":8,"displayName":"Key Passes"},{"value":91,"displayName":"Passes Into Final Third"},{"value":88,"displayName":"Backward Passes"},{"value":8,"displayName":"Goal Kicks"},{"value":10,"displayName":"Interceptions"},{"value":8,"displayName":"Successful Tackles"},{"value":10,"displayName":"Tackles"},{"value":19,"displayName":"Clearances"},{"value":14,"displayName":"Successful Aerial Duels"},{"value":28,"displayName":"Aerial Duels"},{"value":6,"displayName":"Successful Dribbles"},{"value":9,"displayName":"Dribbles"},{"value":0.44,"displayName":"Shots accuracy"},{"value":80,"displayName":"Failed passes"},{"value":0.66,"displayName":"Possession"},{"value":4,"displayName":"Shots on target"},{"value":5,"displayName":"Corners"},{"value":3,"displayName":"Offsides"},{"value":452,"displayName":"Successful passes"},{"value":3,"displayName":"Shots off target"},{"value":2,"displayName":"Blocked shots"},{"value":6,"displayName":"Shots within penalty area"},{"value":532,"displayName":"Total passes"},{"value":3,"displayName":"Shots outside penalty area"},{"value":4,"displayName":"Goalkeeper saves"},{"value":11,"displayName":"Fouls"},{"value":2,"displayName":"Yellow cards"}]}],"id":1183700936,"round":"Regular Season - 14","date":"2025-11-28T20:00:00.000Z","country":{"code":"ES","name":"Spain","logo":"https://highlightly.net/soccer/images/countries/ES.svg"},"state":{"clock":90,"score":{"current":"1 - 0","penalties":null},"description":"Finished"},"awayTeam":{"id":679031,"logo":"https://highlightly.net/soccer/images/teams/679031.png","name":"Elche","topPlayers":[{"name":"Álvaro Rodríguez","position":"Attacker","statistics":[{"name":"Expected Goals","value":0.39},{"name":"Shots On Target","value":2},{"name":"Minutes","value":90}]},{"name":"Marc Aguado","position":"Midfielder","statistics":[{"name":"Expected Goals","value":0},{"name":"Shots On Target","value":0},{"name":"Minutes","value":30}]},{"name":"David Affengruber","position":"Defender","statistics":[{"name":"Interceptions","value":1},{"name":"Clearances","value":7},{"name":"Minutes","value":90}]}],"shots":[{"time":"21\u0027","outcome":"Missed","goalTarget":"Close Right","playerName":"Álvaro Rodríguez"},{"time":"26\u0027","outcome":"Blocked","goalTarget":"Low Centre","playerName":"Grady Diangana"},{"time":"38\u0027","outcome":"Saved","goalTarget":"Low Left","playerName":"Héctor Fort"},{"time":"39\u0027","outcome":"Saved","goalTarget":"Low Left","playerName":"Álvaro Rodríguez"},{"time":"66\u0027","outcome":"Missed","goalTarget":null,"playerName":"Álvaro Rodríguez"},{"time":"75\u0027","outcome":"Saved","goalTarget":"High Centre","playerName":"Álvaro Rodríguez"},{"time":"77\u0027","outcome":"Missed","goalTarget":null,"playerName":"Álvaro Rodríguez"},{"time":"84\u0027","outcome":"Blocked","goalTarget":"Low Right","playerName":"Rafa Mir"},{"time":"90 + 6\u0027","outcome":"Saved","goalTarget":"High Centre","playerName":"David Affengruber"}]},"homeTeam":{"id":465430,"logo":"https://highlightly.net/soccer/images/teams/465430.png","name":"Getafe","topPlayers":[{"name":"Adrian Liso","position":"Attacker","statistics":[{"name":"Expected Goals","value":0.22},{"name":"Shots On Target","value":1},{"name":"Minutes","value":90}]},{"name":"Mauro Arambarri","position":"Midfielder","statistics":[{"name":"Expected Goals","value":0.45},{"name":"Shots On Target","value":2},{"name":"Minutes","value":90}]},{"name":"Domingos Duarte","position":"Defender","statistics":[{"name":"Interceptions","value":0},{"name":"Clearances","value":8},{"name":"Minutes","value":90}]}],"shots":[{"time":"3\u0027","outcome":"Blocked","goalTarget":"Low Left","playerName":"Juan Iglesias"},{"time":"5\u0027","outcome":"Blocked","goalTarget":"Low Centre","playerName":"Mauro Arambarri"},{"time":"7\u0027","outcome":"Missed","goalTarget":null,"playerName":"Alex Sancris"},{"time":"16\u0027","outcome":"Blocked","goalTarget":"Low Right","playerName":"Adrian Liso"},{"time":"17\u0027","outcome":"Saved","goalTarget":"Low Left","playerName":"Allan Nyom"},{"time":"38\u0027","outcome":"Blocked","goalTarget":"Low Centre","playerName":"Allan Nyom"},{"time":"45 + 2\u0027","outcome":"Missed","goalTarget":null,"playerName":"Dakonam Djené"},{"time":"56\u0027","outcome":"Saved","goalTarget":"Low Centre","playerName":"Adrian Liso"},{"time":"56\u0027","outcome":"Blocked","goalTarget":"Low Left","playerName":"Kiko Femenía"},{"time":"56\u0027","outcome":"Goal","goalTarget":"Low Left","playerName":"Mauro Arambarri"},{"time":"67\u0027","outcome":"Saved","goalTarget":"Low Left","playerName":"Alex Sancris"},{"time":"74\u0027","outcome":"Missed","goalTarget":null,"playerName":"Alex Sancris"},{"time":"81\u0027","outcome":"Missed","goalTarget":null,"playerName":"Borja Mayoral"},{"time":"90 + 2\u0027","outcome":"Saved","goalTarget":"Low Centre","playerName":"Mauro Arambarri"},{"time":"90 + 5\u0027","outcome":"Missed","goalTarget":"High Right","playerName":"Juan Iglesias"}]},"league":{"id":119924,"logo":"https://highlightly.net/soccer/images/leagues/119924.png","name":"La Liga","season":2025},"news":[],"lineups":{"homeTeam":{"formation":"4-4-2","substitutes":[{"name":"Jiří Letáček","number":1,"position":"Goalkeeper","id":10705205},{"name":"Diego Rico","number":16,"position":"Defender","id":3037741},{"name":"Jorge Montes","number":41,"position":"Defender","id":null},{"name":"Lucas Laso","number":32,"position":"Defender","id":98168294},{"name":"Hugo Solozábal","number":34,"position":"Midfielder","id":62176261},{"name":"Abu Kamara","number":11,"position":"Forward","id":45795155},{"name":"Yvan Neyou","number":4,"position":"Defender","id":6758290},{"name":"Javier Muñoz","number":14,"position":"Midfielder","id":7544614},{"name":"Coba da Costa","number":20,"position":"Forward","id":49807758},{"name":"José Luis Pérez","number":37,"position":"Forward","id":53672563},{"name":"Juanmi","number":7,"position":"Forward","id":7618674}],"initialLineup":[[{"name":"David Soria","number":13,"position":"Goalkeeper","id":7606921}],[{"name":"Kiko Femenía","number":17,"position":"Defender","id":3025988},{"name":"Domingos Duarte","number":22,"position":"Defender","id":7534149},{"name":"Djené","number":2,"position":"Defender","id":7607404},{"name":"Allan Nyom","number":12,"position":"Defender","id":7632681}],[{"name":"Álex Sancris","number":18,"position":"Midfielder","id":88043326},{"name":"Mauro Arambarri","number":8,"position":"Midfielder","id":7608692},{"name":"Luis Milla","number":5,"position":"Midfielder","id":7580839},{"name":"Juan Iglesias","number":21,"position":"Midfielder","id":19278616}],[{"name":"Adrian Liso","number":23,"position":"Forward","id":63526407},{"name":"Borja Mayoral","number":9,"position":"Forward","id":7643146}]],"id":465430,"logo":"https://highlightly.net/soccer/images/teams/465430.png","name":"Getafe"},"awayTeam":{"formation":"4-4-2","substitutes":[{"name":"Matías Dituro","number":1,"position":"Goalkeeper","id":1826860},{"name":"Alejandro Iturbe","number":45,"position":"Goalkeeper","id":50812398},{"name":"Adrià Pedrosa","number":3,"position":"Defender","id":7620123},{"name":"Bambo Diaby","number":4,"position":"Defender","id":1408260},{"name":"John Nwankwo","number":18,"position":"Defender","id":30568580},{"name":"Pedro Bigas","number":6,"position":"Defender","id":7628012},{"name":"Yago Santiago","number":7,"position":"Forward","id":45790969},{"name":"Rodrigo Mendoza","number":30,"position":"Midfielder","id":54960885},{"name":"Federico Redondo","number":5,"position":"Midfielder","id":50126699},{"name":"Marc Aguado","number":8,"position":"Midfielder","id":30158352},{"name":"Rafa Mir","number":10,"position":"Forward","id":7569247},{"name":"Adam Boayar","number":32,"position":"Forward","id":70726327}],"initialLineup":[[{"name":"Iñaki Peña","number":13,"position":"Goalkeeper","id":20440}],[{"name":"Hector Fort","number":39,"position":"Defender","id":62284453},{"name":"Léo Pétrot","number":21,"position":"Defender","id":25300660},{"name":"David Affengruber","number":22,"position":"Defender","id":20389194},{"name":"Alvaro Núñez","number":15,"position":"Defender","id":29408575}],[{"name":"Germán Valera","number":11,"position":"Midfielder","id":26076197},{"name":"Martim Neto","number":16,"position":"Midfielder","id":43724534},{"name":"Aleix Febas","number":14,"position":"Midfielder","id":7520625},{"name":"Grady Diangana","number":19,"position":"Midfielder","id":3030335}],[{"name":"André Silva","number":9,"position":"Forward","id":332297},{"name":"Álvaro Rodriguez","number":20,"position":"Forward","id":55255676}]],"id":679031,"logo":"https://highlightly.net/soccer/images/teams/679031.png","name":"Elche"}},"boxScore":{"value":[{"team":{"id":465430,"logo":"https://highlightly.net/soccer/images/teams/465430.png","name":"Getafe"},"players":[{"id":7606921,"name":"David Soria","matchRating":"8.55","shirtNumber":13,"position":"Goalkeeper","isCaptain":false,"minutesPlayed":90,"isSubstitute":false,"offsides":0,"statistics":{"goalsScored":0,"goalsSaved":4,"goalsConceded":0,"assists":0,"dribblesTotal":0,"dribblesSuccessful":0,"dribblesFailed":0,"dribbleSuccessRate":"0.00 %","fouledByOthers":0,"fouledOthers":0,"tacklesTotal":0,"interceptionsTotal":0,"shotsOnTarget":0,"shotsOffTarget":0,"shotsTotal":0,"shotsAccuracy":"0.00 %","penaltiesScored":0,"penaltiesMissed":0,"penaltiesTotal":0,"penaltiesAccuracy":"0.00 %","passesAccuracy":"65.22 %","passesSuccessful":15,"passesFailed":8,"passesTotal":23,"passesKey":0,"cardsRed":0,"cardsYellow":0,"cardsSecondYellow":0,"duelsTotal":0,"duelsWon":0,"duelsLost":0,"duelSuccessRate":"0.00 %","expectedAssists":0,"expectedGoals":null,"expectedGoalsOnTarget":null,"expectedGoalsOnTargetConceded":0.69,"expectedGoalsPrevented":0.69},"fullName":"David Soria Solís","logo":null},{"id":19278616,"name":"Juan Iglesias","matchRating":"6.58","shirtNumber":21,"position":"Defender","isCaptain":false,"minutesPlayed":90,"isSubstitute":false,"offsides":0,"statistics":{"goalsScored":0,"goalsSaved":0,"goalsConceded":0,"assists":0,"dribblesTotal":2,"dribblesSuccessful":1,"dribblesFailed":1,"dribbleSuccessRate":"50.00 %","fouledByOthers":3,"fouledOthers":5,"tacklesTotal":3,"interceptionsTotal":1,"shotsOnTarget":0,"shotsOffTarget":1,"shotsTotal":1,"shotsAccuracy":"0.00 %","penaltiesScored":0,"penaltiesMissed":0,"penaltiesTotal":0,"penaltiesAccuracy":"0.00 %","passesAccuracy":"65.00 %","passesSuccessful":13,"passesFailed":7,"passesTotal":20,"passesKey":0,"cardsRed":0,"cardsYellow":0,"cardsSecondYellow":0,"duelsTotal":16,"duelsWon":7,"duelsLost":9,"duelSuccessRate":"43.75 %","expectedAssists":0.02,"expectedGoals":0.03,"expectedGoalsOnTarget":null,"expectedGoalsOnTargetConceded":null,"expectedGoalsPrevented":null},"fullName":"Juan Antonio Iglesias Sánchez","logo":null},{"id":7534149,"name":"Domingos Duarte","matchRating":"7.18","shirtNumber":22,"position":"Defender","isCaptain":false,"minutesPlayed":90,"isSubstitute":false,"offsides":0,"statistics":{"goalsScored":0,"goalsSaved":0,"goalsConceded":0,"assists":0,"dribblesTotal":0,"dribblesSuccessful":0,"dribblesFailed":0,"dribbleSuccessRate":"0.00 %","fouledByOthers":1,"fouledOthers":0,"tacklesTotal":1,"interceptionsTotal":0,"shotsOnTarget":0,"shotsOffTarget":0,"shotsTotal":0,"shotsAccuracy":"0.00 %","penaltiesScored":0,"penaltiesMissed":0,"penaltiesTotal":0,"penaltiesAccuracy":"0.00 %","passesAccuracy":"73.91 %","passesSuccessful":17,"passesFailed":6,"passesTotal":23,"passesKey":0,"cardsRed":0,"cardsYellow":0,"cardsSecondYellow":0,"duelsTotal":6,"duelsWon":5,"duelsLost":1,"duelSuccessRate":"83.33 %","expectedAssists":0,"expectedGoals":null,"expectedGoalsOnTarget":null,"expectedGoalsOnTargetConceded":null,"expectedGoalsPrevented":null},"fullName":"Domingos de Sousa Coutinho Meneses Duar","logo":null},{"id":7607404,"name":"Djené","matchRating":"7.05","shirtNumber":2,"position":"Defender","isCaptain":true,"minutesPlayed":90,"isSubstitute":false,"offsides":0,"statistics":{"goalsScored":0,"goalsSaved":0,"goalsConceded":0,"assists":0,"dribblesTotal":0,"dribblesSuccessful":0,"dribblesFailed":0,"dribbleSuccessRate":"0.00 %","fouledByOthers":1,"fouledOthers":2,"tacklesTotal":2,"interceptionsTotal":1,"shotsOnTarget":0,"shotsOffTarget":1,"shotsTotal":1,"shotsAccuracy":"0.00 %","penaltiesScored":0,"penaltiesMissed":0,"penaltiesTotal":0,"penaltiesAccuracy":"0.00 %","passesAccuracy":"81.82 %","passesSuccessful":18,"passesFailed":4,"passesTotal":22,"passesKey":0,"cardsRed":0,"cardsYellow":1,"cardsSecondYellow":1,"duelsTotal":7,"duelsWon":3,"duelsLost":4,"duelSuccessRate":"42.86 %","expectedAssists":0.01,"expectedGoals":0.02,"expectedGoalsOnTarget":null,"expectedGoalsOnTargetConceded":null,"expectedGoalsPrevented":null},"fullName":"Djené Dakonam Ortega","logo":null},{"id":7632681,"name":"Allan Nyom","matchRating":"7.86","shirtNumber":12,"position":"Defender","isCaptain":false,"minutesPlayed":65,"isSubstitute":false,"offsides":1,"statistics":{"goalsScored":0,"goalsSaved":0,"goalsConceded":0,"assists":0,"dribblesTotal":1,"dribblesSuccessful":1,"dribblesFailed":0,"dribbleSuccessRate":"100.00 %","fouledByOthers":1,"fouledOthers":0,"tacklesTotal":1,"interceptionsTotal":0,"shotsOnTarget":1,"shotsOffTarget":0,"shotsTotal":1,"shotsAccuracy":"100.00 %","penaltiesScored":0,"penaltiesMissed":0,"penaltiesTotal":0,"penaltiesAccuracy":"0.00 %","passesAccuracy":"33.33 %","passesSuccessful":8,"passesFailed":16,"passesTotal":24,"passesKey":2,"cardsRed":0,"cardsYellow":0,"cardsSecondYellow":0,"duelsTotal":10,"duelsWon":9,"duelsLost":1,"duelSuccessRate":"90.00 %","expectedAssists":0.05,"expectedGoals":0.12,"expectedGoalsOnTarget":0.38,"expectedGoalsOnTargetConceded":null,"expectedGoalsPrevented":null},"fullName":"Allan Roméo Nyom","logo":null},{"id":3025988,"name":"Kiko Femenía","matchRating":"7.20","shirtNumber":17,"position":"Midfielder","isCaptain":false,"minutesPlayed":80,"isSubstitute":false,"offsides":0,"statistics":{"goalsScored":0,"goalsSaved":0,"goalsConceded":0,"assists":1,"dribblesTotal":0,"dribblesSuccessful":0,"dribblesFailed":0,"dribbleSuccessRate":"0.00 %","fouledByOthers":1,"fouledOthers":1,"tacklesTotal":0,"interceptionsTotal":0,"shotsOnTarget":1,"shotsOffTarget":0,"shotsTotal":1,"shotsAccuracy":"100.00 %","penaltiesScored":0,"penaltiesMissed":0,"penaltiesTotal":0,"penaltiesAccuracy":"0.00 %","passesAccuracy":"82.61 %","passesSuccessful":19,"passesFailed":4,"passesTotal":23,"passesKey":2,"cardsRed":0,"cardsYellow":0,"cardsSecondYellow":0,"duelsTotal":3,"duelsWon":1,"duelsLost":2,"duelSuccessRate":"33.33 %","expectedAssists":0.1,"expectedGoals":0.04,"expectedGoalsOnTarget":null,"expectedGoalsOnTargetConceded":null,"expectedGoalsPrevented":null},"fullName":"Francisco Femenía Far","logo":null},{"id":7580839,"name":"Luis Milla","matchRating":"6.90","shirtNumber":5,"position":"Midfielder","isCaptain":false,"minutesPlayed":90,"isSubstitute":false,"offsides":0,"statistics":{"goalsScored":0,"goalsSaved":0,"goalsConceded":0,"assists":0,"dribblesTotal":3,"dribblesSuccessful":2,"dribblesFailed":1,"dribbleSuccessRate":"66.67 %","fouledByOthers":1,"fouledOthers":4,"tacklesTotal":2,"interceptionsTotal":1,"shotsOnTarget":0,"shotsOffTarget":0,"shotsTotal":0,"shotsAccuracy":"0.00 %","penaltiesScored":0,"penaltiesMissed":0,"penaltiesTotal":0,"penaltiesAccuracy":"0.00 %","passesAccuracy":"79.41 %","passesSuccessful":27,"passesFailed":7,"passesTotal":34,"passesKey":3,"cardsRed":0,"cardsYellow":1,"cardsSecondYellow":1,"duelsTotal":13,"duelsWon":5,"duelsLost":8,"duelSuccessRate":"38.46 %","expectedAssists":0.38,"expectedGoals":null,"expectedGoalsOnTarget":null,"expectedGoalsOnTargetConceded":null,"expectedGoalsPrevented":null},"fullName":"Luis Milla Manzanares","logo":null},{"id":7608692,"name":"Mauro Arambarri","matchRating":"7.55","shirtNumber":8,"position":"Midfielder","isCaptain":false,"minutesPlayed":90,"isSubstitute":false,"offsides":0,"statistics":{"goalsScored":1,"goalsSaved":0,"goalsConceded":0,"assists":0,"dribblesTotal":0,"dribblesSuccessful":0,"dribblesFailed":0,"dribbleSuccessRate":"0.00 %","fouledByOthers":2,"fouledOthers":3,"tacklesTotal":2,"interceptionsTotal":1,"shotsOnTarget":2,"shotsOffTarget":0,"shotsTotal":2,"shotsAccuracy":"100.00 %","penaltiesScored":0,"penaltiesMissed":0,"penaltiesTotal":0,"penaltiesAccuracy":"0.00 %","passesAccuracy":"80.00 %","passesSuccessful":20,"passesFailed":5,"passesTotal":25,"passesKey":1,"cardsRed":0,"cardsYellow":0,"cardsSecondYellow":0,"duelsTotal":12,"duelsWon":7,"duelsLost":5,"duelSuccessRate":"58.33 %","expectedAssists":0.01,"expectedGoals":0.45,"expectedGoalsOnTarget":0.94,"expectedGoalsOnTargetConceded":null,"expectedGoalsPrevented":null},"fullName":"Mauro Wilney Arambarri Rosa","logo":null},{"id":29698053,"name":"Álex Sancris","matchRating":"6.70","shirtNumber":18,"position":"Midfielder","isCaptain":false,"minutesPlayed":80,"isSubstitute":false,"offsides":1,"statistics":{"goalsScored":0,"goalsSaved":0,"goalsConceded":0,"assists":0,"dribblesTotal":0,"dribblesSuccessful":0,"dribblesFailed":0,"dribbleSuccessRate":"0.00 %","fouledByOthers":0,"fouledOthers":1,"tacklesTotal":1,"interceptionsTotal":0,"shotsOnTarget":1,"shotsOffTarget":2,"shotsTotal":3,"shotsAccuracy":"33.33 %","penaltiesScored":0,"penaltiesMissed":0,"penaltiesTotal":0,"penaltiesAccuracy":"0.00 %","passesAccuracy":"46.15 %","passesSuccessful":6,"passesFailed":7,"passesTotal":13,"passesKey":0,"cardsRed":0,"cardsYellow":0,"cardsSecondYellow":0,"duelsTotal":5,"duelsWon":1,"duelsLost":4,"duelSuccessRate":"20.00 %","expectedAssists":0,"expectedGoals":0.16,"expectedGoalsOnTarget":0.18,"expectedGoalsOnTargetConceded":null,"expectedGoalsPrevented":null},"fullName":"Alejandro San Cristóbal Sánchez","logo":null},{"id":63526407,"name":"Adrian Liso","matchRating":"6.72","shirtNumber":23,"position":"Forward","isCaptain":false,"minutesPlayed":90,"isSubstitute":false,"offsides":0,"statistics":{"goalsScored":0,"goalsSaved":0,"goalsConceded":0,"assists":0,"dribblesTotal":1,"dribblesSuccessful":0,"dribblesFailed":1,"dribbleSuccessRate":"0.00 %","fouledByOthers":1,"fouledOthers":0,"tacklesTotal":0,"interceptionsTotal":0,"shotsOnTarget":1,"shotsOffTarget":0,"shotsTotal":1,"shotsAccuracy":"100.00 %","penaltiesScored":0,"penaltiesMissed":0,"penaltiesTotal":0,"penaltiesAccuracy":"0.00 %","passesAccuracy":"66.67 %","passesSuccessful":10,"passesFailed":5,"passesTotal":15,"passesKey":0,"cardsRed":0,"cardsYellow":0,"cardsSecondYellow":0,"duelsTotal":6,"duelsWon":2,"duelsLost":4,"duelSuccessRate":"33.33 %","expectedAssists":0,"expectedGoals":0.22,"expectedGoalsOnTarget":0.16,"expectedGoalsOnTargetConceded":null,"expectedGoalsPrevented":null},"fullName":"Adrian Liso Lahoz","logo":null},{"id":7643146,"name":"Borja Mayoral","matchRating":"6.32","shirtNumber":9,"position":"Forward","isCaptain":false,"minutesPlayed":89,"isSubstitute":false,"offsides":0,"statistics":{"goalsScored":0,"goalsSaved":0,"goalsConceded":0,"assists":0,"dribblesTotal":0,"dribblesSuccessful":0,"dribblesFailed":0,"dribbleSuccessRate":"0.00 %","fouledByOthers":0,"fouledOthers":1,"tacklesTotal":0,"interceptionsTotal":0,"shotsOnTarget":0,"shotsOffTarget":1,"shotsTotal":1,"shotsAccuracy":"0.00 %","penaltiesScored":0,"penaltiesMissed":0,"penaltiesTotal":0,"penaltiesAccuracy":"0.00 %","passesAccuracy":"95.24 %","passesSuccessful":20,"passesFailed":1,"passesTotal":21,"passesKey":0,"cardsRed":0,"cardsYellow":0,"cardsSecondYellow":0,"duelsTotal":8,"duelsWon":1,"duelsLost":7,"duelSuccessRate":"12.50 %","expectedAssists":0.02,"expectedGoals":0.01,"expectedGoalsOnTarget":null,"expectedGoalsOnTargetConceded":null,"expectedGoalsPrevented":null},"fullName":"Borja Mayoral Moya","logo":null},{"id":3037741,"name":"Diego Rico","matchRating":"6.72","shirtNumber":16,"position":"Defender","isCaptain":false,"minutesPlayed":25,"isSubstitute":true,"offsides":0,"statistics":{"goalsScored":0,"goalsSaved":0,"goalsConceded":0,"assists":0,"dribblesTotal":0,"dribblesSuccessful":0,"dribblesFailed":0,"dribbleSuccessRate":"0.00 %","fouledByOthers":0,"fouledOthers":1,"tacklesTotal":0,"interceptionsTotal":0,"shotsOnTarget":0,"shotsOffTarget":0,"shotsTotal":0,"shotsAccuracy":"0.00 %","penaltiesScored":0,"penaltiesMissed":0,"penaltiesTotal":0,"penaltiesAccuracy":"0.00 %","passesAccuracy":"25.00 %","passesSuccessful":1,"passesFailed":3,"passesTotal":4,"passesKey":0,"cardsRed":0,"cardsYellow":0,"cardsSecondYellow":0,"duelsTotal":1,"duelsWon":0,"duelsLost":1,"duelSuccessRate":"0.00 %","expectedAssists":0,"expectedGoals":null,"expectedGoalsOnTarget":null,"expectedGoalsOnTargetConceded":null,"expectedGoalsPrevented":null},"fullName":"Diego Rico Salguero","logo":null},{"id":45795155,"name":"Abu Kamara","matchRating":"6.70","shirtNumber":11,"position":"Forward","isCaptain":false,"minutesPlayed":10,"isSubstitute":true,"offsides":0,"statistics":{"goalsScored":0,"goalsSaved":0,"goalsConceded":0,"assists":0,"dribblesTotal":0,"dribblesSuccessful":0,"dribblesFailed":0,"dribbleSuccessRate":"0.00 %","fouledByOthers":0,"fouledOthers":0,"tacklesTotal":1,"interceptionsTotal":0,"shotsOnTarget":0,"shotsOffTarget":0,"shotsTotal":0,"shotsAccuracy":"0.00 %","penaltiesScored":0,"penaltiesMissed":0,"penaltiesTotal":0,"penaltiesAccuracy":"0.00 %","passesAccuracy":"66.67 %","passesSuccessful":2,"passesFailed":1,"passesTotal":3,"passesKey":1,"cardsRed":0,"cardsYellow":0,"cardsSecondYellow":0,"duelsTotal":1,"duelsWon":1,"duelsLost":0,"duelSuccessRate":"100.00 %","expectedAssists":0,"expectedGoals":null,"expectedGoalsOnTarget":null,"expectedGoalsOnTargetConceded":null,"expectedGoalsPrevented":null},"fullName":"Abu Kamara","logo":null},{"id":7544614,"name":"Javier Muñoz","matchRating":"6.55","shirtNumber":14,"position":"Midfielder","isCaptain":false,"minutesPlayed":10,"isSubstitute":true,"offsides":0,"statistics":{"goalsScored":0,"goalsSaved":0,"goalsConceded":0,"assists":0,"dribblesTotal":1,"dribblesSuccessful":0,"dribblesFailed":1,"dribbleSuccessRate":"0.00 %","fouledByOthers":0,"fouledOthers":0,"tacklesTotal":0,"interceptionsTotal":0,"shotsOnTarget":0,"shotsOffTarget":0,"shotsTotal":0,"shotsAccuracy":"0.00 %","penaltiesScored":0,"penaltiesMissed":0,"penaltiesTotal":0,"penaltiesAccuracy":"0.00 %","passesAccuracy":"20.00 %","passesSuccessful":1,"passesFailed":4,"passesTotal":5,"passesKey":0,"cardsRed":0,"cardsYellow":0,"cardsSecondYellow":0,"duelsTotal":1,"duelsWon":0,"duelsLost":1,"duelSuccessRate":"0.00 %","expectedAssists":0,"expectedGoals":null,"expectedGoalsOnTarget":null,"expectedGoalsOnTargetConceded":null,"expectedGoalsPrevented":null},"fullName":"Javier Muñoz Jiménez","logo":null},{"id":6758290,"name":"Yvan Neyou","matchRating":null,"shirtNumber":4,"position":"Defender","isCaptain":false,"minutesPlayed":1,"isSubstitute":true,"offsides":0,"statistics":{"goalsScored":0,"goalsSaved":0,"goalsConceded":0,"assists":0,"dribblesTotal":0,"dribblesSuccessful":0,"dribblesFailed":0,"dribbleSuccessRate":"0.00 %","fouledByOthers":0,"fouledOthers":0,"tacklesTotal":0,"interceptionsTotal":0,"shotsOnTarget":0,"shotsOffTarget":0,"shotsTotal":0,"shotsAccuracy":"0.00 %","penaltiesScored":0,"penaltiesMissed":0,"penaltiesTotal":0,"penaltiesAccuracy":"0.00 %","passesAccuracy":"66.67 %","passesSuccessful":2,"passesFailed":1,"passesTotal":3,"passesKey":0,"cardsRed":0,"cardsYellow":0,"cardsSecondYellow":0,"duelsTotal":0,"duelsWon":0,"duelsLost":0,"duelSuccessRate":"0.00 %","expectedAssists":0,"expectedGoals":null,"expectedGoalsOnTarget":null,"expectedGoalsOnTargetConceded":null,"expectedGoalsPrevented":null},"fullName":"Yvan Latour Neyou Noupa","logo":null},{"id":10705205,"name":"Jiří Letáček","matchRating":null,"shirtNumber":1,"position":"Goalkeeper","isCaptain":false,"minutesPlayed":0,"isSubstitute":true,"offsides":0,"statistics":{"goalsScored":0,"goalsSaved":0,"goalsConceded":0,"assists":0,"dribblesTotal":0,"dribblesSuccessful":0,"dribblesFailed":0,"dribbleSuccessRate":"0.00 %","fouledByOthers":0,"fouledOthers":0,"tacklesTotal":0,"interceptionsTotal":0,"shotsOnTarget":0,"shotsOffTarget":0,"shotsTotal":0,"shotsAccuracy":"0.00 %","penaltiesScored":0,"penaltiesMissed":0,"penaltiesTotal":0,"penaltiesAccuracy":"0.00 %","passesAccuracy":"0.00 %","passesSuccessful":0,"passesFailed":0,"passesTotal":0,"passesKey":0,"cardsRed":0,"cardsYellow":0,"cardsSecondYellow":0,"duelsTotal":0,"duelsWon":0,"duelsLost":0,"duelSuccessRate":"0.00 %","expectedAssists":null,"expectedGoals":null,"expectedGoalsOnTarget":null,"expectedGoalsOnTargetConceded":null,"expectedGoalsPrevented":null},"fullName":"Jiří Letáček","logo":null},{"id":100727550,"name":"Jorge Montes","matchRating":null,"shirtNumber":41,"position":"Defender","isCaptain":false,"minutesPlayed":0,"isSubstitute":true,"offsides":0,"statistics":{"goalsScored":0,"goalsSaved":0,"goalsConceded":0,"assists":0,"dribblesTotal":0,"dribblesSuccessful":0,"dribblesFailed":0,"dribbleSuccessRate":"0.00 %","fouledByOthers":0,"fouledOthers":0,"tacklesTotal":0,"interceptionsTotal":0,"shotsOnTarget":0,"shotsOffTarget":0,"shotsTotal":0,"shotsAccuracy":"0.00 %","penaltiesScored":0,"penaltiesMissed":0,"penaltiesTotal":0,"penaltiesAccuracy":"0.00 %","passesAccuracy":"0.00 %","passesSuccessful":0,"passesFailed":0,"passesTotal":0,"passesKey":0,"cardsRed":0,"cardsYellow":0,"cardsSecondYellow":0,"duelsTotal":0,"duelsWon":0,"duelsLost":0,"duelSuccessRate":"0.00 %","expectedAssists":null,"expectedGoals":null,"expectedGoalsOnTarget":null,"expectedGoalsOnTargetConceded":null,"expectedGoalsPrevented":null},"fullName":null,"logo":null},{"id":98168294,"name":"Lucas Laso","matchRating":null,"shirtNumber":32,"position":"Defender","isCaptain":false,"minutesPlayed":0,"isSubstitute":true,"offsides":0,"statistics":{"goalsScored":0,"goalsSaved":0,"goalsConceded":0,"assists":0,"dribblesTotal":0,"dribblesSuccessful":0,"dribblesFailed":0,"dribbleSuccessRate":"0.00 %","fouledByOthers":0,"fouledOthers":0,"tacklesTotal":0,"interceptionsTotal":0,"shotsOnTarget":0,"shotsOffTarget":0,"shotsTotal":0,"shotsAccuracy":"0.00 %","penaltiesScored":0,"penaltiesMissed":0,"penaltiesTotal":0,"penaltiesAccuracy":"0.00 %","passesAccuracy":"0.00 %","passesSuccessful":0,"passesFailed":0,"passesTotal":0,"passesKey":0,"cardsRed":0,"cardsYellow":0,"cardsSecondYellow":0,"duelsTotal":0,"duelsWon":0,"duelsLost":0,"duelSuccessRate":"0.00 %","expectedAssists":0.38,"expectedGoals":null,"expectedGoalsOnTarget":null,"expectedGoalsOnTargetConceded":null,"expectedGoalsPrevented":null},"fullName":null,"logo":null},{"id":62176261,"name":"Hugo Solozábal","matchRating":null,"shirtNumber":34,"position":"Midfielder","isCaptain":false,"minutesPlayed":0,"isSubstitute":true,"offsides":0,"statistics":{"goalsScored":0,"goalsSaved":0,"goalsConceded":0,"assists":0,"dribblesTotal":0,"dribblesSuccessful":0,"dribblesFailed":0,"dribbleSuccessRate":"0.00 %","fouledByOthers":0,"fouledOthers":0,"tacklesTotal":0,"interceptionsTotal":0,"shotsOnTarget":0,"shotsOffTarget":0,"shotsTotal":0,"shotsAccuracy":"0.00 %","penaltiesScored":0,"penaltiesMissed":0,"penaltiesTotal":0,"penaltiesAccuracy":"0.00 %","passesAccuracy":"0.00 %","passesSuccessful":0,"passesFailed":0,"passesTotal":0,"passesKey":0,"cardsRed":0,"cardsYellow":0,"cardsSecondYellow":0,"duelsTotal":0,"duelsWon":0,"duelsLost":0,"duelSuccessRate":"0.00 %","expectedAssists":null,"expectedGoals":null,"expectedGoalsOnTarget":null,"expectedGoalsOnTargetConceded":null,"expectedGoalsPrevented":null},"fullName":"Hugo Solozábal Granados","logo":null},{"id":49807758,"name":"Coba Da Costa","matchRating":null,"shirtNumber":20,"position":"Forward","isCaptain":false,"minutesPlayed":0,"isSubstitute":true,"offsides":0,"statistics":{"goalsScored":0,"goalsSaved":0,"goalsConceded":0,"assists":0,"dribblesTotal":0,"dribblesSuccessful":0,"dribblesFailed":0,"dribbleSuccessRate":"0.00 %","fouledByOthers":0,"fouledOthers":0,"tacklesTotal":0,"interceptionsTotal":0,"shotsOnTarget":0,"shotsOffTarget":0,"shotsTotal":0,"shotsAccuracy":"0.00 %","penaltiesScored":0,"penaltiesMissed":0,"penaltiesTotal":0,"penaltiesAccuracy":"0.00 %","passesAccuracy":"0.00 %","passesSuccessful":0,"passesFailed":0,"passesTotal":0,"passesKey":0,"cardsRed":0,"cardsYellow":0,"cardsSecondYellow":0,"duelsTotal":0,"duelsWon":0,"duelsLost":0,"duelSuccessRate":"0.00 %","expectedAssists":null,"expectedGoals":null,"expectedGoalsOnTarget":null,"expectedGoalsOnTargetConceded":null,"expectedGoalsPrevented":null},"fullName":"Coba Gomes da Costa","logo":null},{"id":53672563,"name":"José Luis Pérez","matchRating":null,"shirtNumber":37,"position":"Forward","isCaptain":false,"minutesPlayed":0,"isSubstitute":true,"offsides":0,"statistics":{"goalsScored":0,"goalsSaved":0,"goalsConceded":0,"assists":0,"dribblesTotal":0,"dribblesSuccessful":0,"dribblesFailed":0,"dribbleSuccessRate":"0.00 %","fouledByOthers":0,"fouledOthers":0,"tacklesTotal":0,"interceptionsTotal":0,"shotsOnTarget":0,"shotsOffTarget":0,"shotsTotal":0,"shotsAccuracy":"0.00 %","penaltiesScored":0,"penaltiesMissed":0,"penaltiesTotal":0,"penaltiesAccuracy":"0.00 %","passesAccuracy":"0.00 %","passesSuccessful":0,"passesFailed":0,"passesTotal":0,"passesKey":0,"cardsRed":0,"cardsYellow":0,"cardsSecondYellow":0,"duelsTotal":0,"duelsWon":0,"duelsLost":0,"duelSuccessRate":"0.00 %","expectedAssists":null,"expectedGoals":null,"expectedGoalsOnTarget":null,"expectedGoalsOnTargetConceded":null,"expectedGoalsPrevented":null},"fullName":"José Luis Pérez del Amo","logo":null},{"id":7618674,"name":"Juanmi","matchRating":null,"shirtNumber":7,"position":"Forward","isCaptain":false,"minutesPlayed":0,"isSubstitute":true,"offsides":0,"statistics":{"goalsScored":0,"goalsSaved":0,"goalsConceded":0,"assists":0,"dribblesTotal":0,"dribblesSuccessful":0,"dribblesFailed":0,"dribbleSuccessRate":"0.00 %","fouledByOthers":0,"fouledOthers":0,"tacklesTotal":0,"interceptionsTotal":0,"shotsOnTarget":0,"shotsOffTarget":0,"shotsTotal":0,"shotsAccuracy":"0.00 %","penaltiesScored":0,"penaltiesMissed":0,"penaltiesTotal":0,"penaltiesAccuracy":"0.00 %","passesAccuracy":"0.00 %","passesSuccessful":0,"passesFailed":0,"passesTotal":0,"passesKey":0,"cardsRed":0,"cardsYellow":0,"cardsSecondYellow":0,"duelsTotal":0,"duelsWon":0,"duelsLost":0,"duelSuccessRate":"0.00 %","expectedAssists":0.02,"expectedGoals":0.03,"expectedGoalsOnTarget":null,"expectedGoalsOnTargetConceded":null,"expectedGoalsPrevented":null},"fullName":"Juan Miguel Jiménez López","logo":null}]},{"team":{"id":679031,"logo":"https://highlightly.net/soccer/images/teams/679031.png","name":"Elche"},"players":[{"id":20440,"name":"Iñaki Peña","matchRating":"8.92","shirtNumber":13,"position":"Goalkeeper","isCaptain":false,"minutesPlayed":90,"isSubstitute":false,"offsides":0,"statistics":{"goalsScored":0,"goalsSaved":4,"goalsConceded":1,"assists":0,"dribblesTotal":0,"dribblesSuccessful":0,"dribblesFailed":0,"dribbleSuccessRate":"0.00 %","fouledByOthers":0,"fouledOthers":0,"tacklesTotal":0,"interceptionsTotal":0,"shotsOnTarget":0,"shotsOffTarget":0,"shotsTotal":0,"shotsAccuracy":"0.00 %","penaltiesScored":0,"penaltiesMissed":0,"penaltiesTotal":0,"penaltiesAccuracy":"0.00 %","passesAccuracy":"75.51 %","passesSuccessful":37,"passesFailed":12,"passesTotal":49,"passesKey":0,"cardsRed":0,"cardsYellow":0,"cardsSecondYellow":0,"duelsTotal":0,"duelsWon":0,"duelsLost":0,"duelSuccessRate":"0.00 %","expectedAssists":0,"expectedGoals":null,"expectedGoalsOnTarget":null,"expectedGoalsOnTargetConceded":1.7,"expectedGoalsPrevented":0.67},"fullName":"Ignacio Peña Sotorres","logo":null},{"id":62284453,"name":"Hector Fort","matchRating":"6.21","shirtNumber":39,"position":"Defender","isCaptain":false,"minutesPlayed":64,"isSubstitute":false,"offsides":0,"statistics":{"goalsScored":0,"goalsSaved":0,"goalsConceded":0,"assists":0,"dribblesTotal":2,"dribblesSuccessful":1,"dribblesFailed":1,"dribbleSuccessRate":"50.00 %","fouledByOthers":0,"fouledOthers":0,"tacklesTotal":0,"interceptionsTotal":0,"shotsOnTarget":1,"shotsOffTarget":0,"shotsTotal":1,"shotsAccuracy":"100.00 %","penaltiesScored":0,"penaltiesMissed":0,"penaltiesTotal":0,"penaltiesAccuracy":"0.00 %","passesAccuracy":"80.77 %","passesSuccessful":21,"passesFailed":5,"passesTotal":26,"passesKey":1,"cardsRed":0,"cardsYellow":0,"cardsSecondYellow":0,"duelsTotal":5,"duelsWon":2,"duelsLost":3,"duelSuccessRate":"40.00 %","expectedAssists":0.04,"expectedGoals":0.02,"expectedGoalsOnTarget":0.13,"expectedGoalsOnTargetConceded":null,"expectedGoalsPrevented":null},"fullName":"Héctor Fort García","logo":null},{"id":29408575,"name":"Alvaro Núñez","matchRating":"7.22","shirtNumber":15,"position":"Defender","isCaptain":false,"minutesPlayed":90,"isSubstitute":false,"offsides":0,"statistics":{"goalsScored":0,"goalsSaved":0,"goalsConceded":0,"assists":0,"dribblesTotal":1,"dribblesSuccessful":1,"dribblesFailed":0,"dribbleSuccessRate":"100.00 %","fouledByOthers":1,"fouledOthers":0,"tacklesTotal":1,"interceptionsTotal":1,"shotsOnTarget":0,"shotsOffTarget":0,"shotsTotal":0,"shotsAccuracy":"0.00 %","penaltiesScored":0,"penaltiesMissed":0,"penaltiesTotal":0,"penaltiesAccuracy":"0.00 %","passesAccuracy":"90.79 %","passesSuccessful":69,"passesFailed":7,"passesTotal":76,"passesKey":0,"cardsRed":0,"cardsYellow":0,"cardsSecondYellow":0,"duelsTotal":8,"duelsWon":5,"duelsLost":3,"duelSuccessRate":"62.50 %","expectedAssists":0.05,"expectedGoals":null,"expectedGoalsOnTarget":null,"expectedGoalsOnTargetConceded":null,"expectedGoalsPrevented":null},"fullName":"Álvaro Núñez Cobo","logo":null},{"id":20389194,"name":"David Affengruber","matchRating":"7.23","shirtNumber":22,"position":"Defender","isCaptain":false,"minutesPlayed":90,"isSubstitute":false,"offsides":0,"statistics":{"goalsScored":0,"goalsSaved":0,"goalsConceded":0,"assists":0,"dribblesTotal":0,"dribblesSuccessful":0,"dribblesFailed":0,"dribbleSuccessRate":"0.00 %","fouledByOthers":0,"fouledOthers":0,"tacklesTotal":0,"interceptionsTotal":1,"shotsOnTarget":1,"shotsOffTarget":0,"shotsTotal":1,"shotsAccuracy":"100.00 %","penaltiesScored":0,"penaltiesMissed":0,"penaltiesTotal":0,"penaltiesAccuracy":"0.00 %","passesAccuracy":"90.14 %","passesSuccessful":64,"passesFailed":7,"passesTotal":71,"passesKey":0,"cardsRed":0,"cardsYellow":0,"cardsSecondYellow":0,"duelsTotal":5,"duelsWon":2,"duelsLost":3,"duelSuccessRate":"40.00 %","expectedAssists":0.02,"expectedGoals":0.05,"expectedGoalsOnTarget":0.2,"expectedGoalsOnTargetConceded":null,"expectedGoalsPrevented":null},"fullName":"David Affengruber","logo":null},{"id":25300660,"name":"Léo Pétrot","matchRating":"6.73","shirtNumber":21,"position":"Defender","isCaptain":false,"minutesPlayed":90,"isSubstitute":false,"offsides":0,"statistics":{"goalsScored":0,"goalsSaved":0,"goalsConceded":0,"assists":0,"dribblesTotal":1,"dribblesSuccessful":1,"dribblesFailed":0,"dribbleSuccessRate":"100.00 %","fouledByOthers":0,"fouledOthers":1,"tacklesTotal":0,"interceptionsTotal":0,"shotsOnTarget":0,"shotsOffTarget":0,"shotsTotal":0,"shotsAccuracy":"0.00 %","penaltiesScored":0,"penaltiesMissed":0,"penaltiesTotal":0,"penaltiesAccuracy":"0.00 %","passesAccuracy":"89.29 %","passesSuccessful":50,"passesFailed":6,"passesTotal":56,"passesKey":0,"cardsRed":0,"cardsYellow":0,"cardsSecondYellow":0,"duelsTotal":6,"duelsWon":4,"duelsLost":2,"duelSuccessRate":"66.67 %","expectedAssists":0.03,"expectedGoals":null,"expectedGoalsOnTarget":null,"expectedGoalsOnTargetConceded":null,"expectedGoalsPrevented":null},"fullName":"Léo Pétrot","logo":null},{"id":26076197,"name":"Germán Valera","matchRating":"6.92","shirtNumber":11,"position":"Defender","isCaptain":false,"minutesPlayed":72,"isSubstitute":false,"offsides":0,"statistics":{"goalsScored":0,"goalsSaved":0,"goalsConceded":0,"assists":0,"dribblesTotal":1,"dribblesSuccessful":1,"dribblesFailed":0,"dribbleSuccessRate":"100.00 %","fouledByOthers":4,"fouledOthers":2,"tacklesTotal":2,"interceptionsTotal":1,"shotsOnTarget":0,"shotsOffTarget":0,"shotsTotal":0,"shotsAccuracy":"0.00 %","penaltiesScored":0,"penaltiesMissed":0,"penaltiesTotal":0,"penaltiesAccuracy":"0.00 %","passesAccuracy":"86.36 %","passesSuccessful":19,"passesFailed":3,"passesTotal":22,"passesKey":0,"cardsRed":0,"cardsYellow":0,"cardsSecondYellow":0,"duelsTotal":10,"duelsWon":7,"duelsLost":3,"duelSuccessRate":"70.00 %","expectedAssists":0.01,"expectedGoals":null,"expectedGoalsOnTarget":null,"expectedGoalsOnTargetConceded":null,"expectedGoalsPrevented":null},"fullName":"Germán Valera Karabinaite","logo":null},{"id":3030335,"name":"Grady Diangana","matchRating":"6.48","shirtNumber":19,"position":"Midfielder","isCaptain":false,"minutesPlayed":45,"isSubstitute":false,"offsides":1,"statistics":{"goalsScored":0,"goalsSaved":0,"goalsConceded":0,"assists":0,"dribblesTotal":0,"dribblesSuccessful":0,"dribblesFailed":0,"dribbleSuccessRate":"0.00 %","fouledByOthers":0,"fouledOthers":1,"tacklesTotal":0,"interceptionsTotal":0,"shotsOnTarget":0,"shotsOffTarget":0,"shotsTotal":0,"shotsAccuracy":"0.00 %","penaltiesScored":0,"penaltiesMissed":0,"penaltiesTotal":0,"penaltiesAccuracy":"0.00 %","passesAccuracy":"87.50 %","passesSuccessful":14,"passesFailed":2,"passesTotal":16,"passesKey":1,"cardsRed":0,"cardsYellow":0,"cardsSecondYellow":0,"duelsTotal":4,"duelsWon":0,"duelsLost":4,"duelSuccessRate":"0.00 %","expectedAssists":0.06,"expectedGoals":0.04,"expectedGoalsOnTarget":null,"expectedGoalsOnTargetConceded":null,"expectedGoalsPrevented":null},"fullName":"Grady George Diangana","logo":null},{"id":7520625,"name":"Aleix Febas","matchRating":"6.98","shirtNumber":14,"position":"Midfielder","isCaptain":true,"minutesPlayed":90,"isSubstitute":false,"offsides":0,"statistics":{"goalsScored":0,"goalsSaved":0,"goalsConceded":0,"assists":0,"dribblesTotal":1,"dribblesSuccessful":1,"dribblesFailed":0,"dribbleSuccessRate":"100.00 %","fouledByOthers":5,"fouledOthers":3,"tacklesTotal":3,"interceptionsTotal":1,"shotsOnTarget":0,"shotsOffTarget":0,"shotsTotal":0,"shotsAccuracy":"0.00 %","penaltiesScored":0,"penaltiesMissed":0,"penaltiesTotal":0,"penaltiesAccuracy":"0.00 %","passesAccuracy":"92.06 %","passesSuccessful":58,"passesFailed":5,"passesTotal":63,"passesKey":0,"cardsRed":0,"cardsYellow":0,"cardsSecondYellow":0,"duelsTotal":15,"duelsWon":9,"duelsLost":6,"duelSuccessRate":"60.00 %","expectedAssists":0.04,"expectedGoals":null,"expectedGoalsOnTarget":null,"expectedGoalsOnTargetConceded":null,"expectedGoalsPrevented":null},"fullName":"Aleix Febas Pérez","logo":null},{"id":43724534,"name":"Martim Neto","matchRating":"6.75","shirtNumber":16,"position":"Midfielder","isCaptain":false,"minutesPlayed":61,"isSubstitute":false,"offsides":0,"statistics":{"goalsScored":0,"goalsSaved":0,"goalsConceded":0,"assists":0,"dribblesTotal":1,"dribblesSuccessful":1,"dribblesFailed":0,"dribbleSuccessRate":"100.00 %","fouledByOthers":0,"fouledOthers":0,"tacklesTotal":2,"interceptionsTotal":0,"shotsOnTarget":0,"shotsOffTarget":0,"shotsTotal":0,"shotsAccuracy":"0.00 %","penaltiesScored":0,"penaltiesMissed":0,"penaltiesTotal":0,"penaltiesAccuracy":"0.00 %","passesAccuracy":"82.05 %","passesSuccessful":32,"passesFailed":7,"passesTotal":39,"passesKey":0,"cardsRed":0,"cardsYellow":0,"cardsSecondYellow":0,"duelsTotal":5,"duelsWon":3,"duelsLost":2,"duelSuccessRate":"60.00 %","expectedAssists":0.02,"expectedGoals":null,"expectedGoalsOnTarget":null,"expectedGoalsOnTargetConceded":null,"expectedGoalsPrevented":null},"fullName":"Martim Carvalho Neto","logo":null},{"id":55255676,"name":"Álvaro Rodriguez","matchRating":"6.92","shirtNumber":20,"position":"Forward","isCaptain":false,"minutesPlayed":90,"isSubstitute":false,"offsides":1,"statistics":{"goalsScored":0,"goalsSaved":0,"goalsConceded":0,"assists":0,"dribblesTotal":0,"dribblesSuccessful":0,"dribblesFailed":0,"dribbleSuccessRate":"0.00 %","fouledByOthers":2,"fouledOthers":1,"tacklesTotal":0,"interceptionsTotal":1,"shotsOnTarget":2,"shotsOffTarget":3,"shotsTotal":5,"shotsAccuracy":"40.00 %","penaltiesScored":0,"penaltiesMissed":0,"penaltiesTotal":0,"penaltiesAccuracy":"0.00 %","passesAccuracy":"72.22 %","passesSuccessful":13,"passesFailed":5,"passesTotal":18,"passesKey":2,"cardsRed":0,"cardsYellow":0,"cardsSecondYellow":0,"duelsTotal":10,"duelsWon":6,"duelsLost":4,"duelSuccessRate":"60.00 %","expectedAssists":0.02,"expectedGoals":0.39,"expectedGoalsOnTarget":0.37,"expectedGoalsOnTargetConceded":null,"expectedGoalsPrevented":null},"fullName":"Álvaro Daniel Rodríguez Muñoz","logo":null},{"id":332297,"name":"André Silva","matchRating":"6.32","shirtNumber":9,"position":"Forward","isCaptain":false,"minutesPlayed":71,"isSubstitute":false,"offsides":1,"statistics":{"goalsScored":0,"goalsSaved":0,"goalsConceded":0,"assists":0,"dribblesTotal":1,"dribblesSuccessful":0,"dribblesFailed":1,"dribbleSuccessRate":"0.00 %","fouledByOthers":0,"fouledOthers":1,"tacklesTotal":0,"interceptionsTotal":1,"shotsOnTarget":0,"shotsOffTarget":0,"shotsTotal":0,"shotsAccuracy":"0.00 %","penaltiesScored":0,"penaltiesMissed":0,"penaltiesTotal":0,"penaltiesAccuracy":"0.00 %","passesAccuracy":"76.47 %","passesSuccessful":13,"passesFailed":4,"passesTotal":17,"passesKey":1,"cardsRed":0,"cardsYellow":0,"cardsSecondYellow":0,"duelsTotal":5,"duelsWon":0,"duelsLost":5,"duelSuccessRate":"0.00 %","expectedAssists":0.03,"expectedGoals":null,"expectedGoalsOnTarget":null,"expectedGoalsOnTargetConceded":null,"expectedGoalsPrevented":null},"fullName":"André Miguel Valente da Silva","logo":null},{"id":54960885,"name":"Rodrigo Mendoza","matchRating":"6.51","shirtNumber":30,"position":"Midfielder","isCaptain":false,"minutesPlayed":45,"isSubstitute":true,"offsides":0,"statistics":{"goalsScored":0,"goalsSaved":0,"goalsConceded":0,"assists":0,"dribblesTotal":0,"dribblesSuccessful":0,"dribblesFailed":0,"dribbleSuccessRate":"0.00 %","fouledByOthers":2,"fouledOthers":1,"tacklesTotal":0,"interceptionsTotal":1,"shotsOnTarget":0,"shotsOffTarget":0,"shotsTotal":0,"shotsAccuracy":"0.00 %","penaltiesScored":0,"penaltiesMissed":0,"penaltiesTotal":0,"penaltiesAccuracy":"0.00 %","passesAccuracy":"74.07 %","passesSuccessful":20,"passesFailed":7,"passesTotal":27,"passesKey":0,"cardsRed":0,"cardsYellow":1,"cardsSecondYellow":1,"duelsTotal":8,"duelsWon":4,"duelsLost":4,"duelSuccessRate":"50.00 %","expectedAssists":0.02,"expectedGoals":null,"expectedGoalsOnTarget":null,"expectedGoalsOnTargetConceded":null,"expectedGoalsPrevented":null},"fullName":"Rodrigo Mendoza Martinez Moya","logo":null},{"id":30158352,"name":"Marc Aguado","matchRating":"6.98","shirtNumber":8,"position":"Midfielder","isCaptain":false,"minutesPlayed":29,"isSubstitute":true,"offsides":0,"statistics":{"goalsScored":0,"goalsSaved":0,"goalsConceded":0,"assists":0,"dribblesTotal":0,"dribblesSuccessful":0,"dribblesFailed":0,"dribbleSuccessRate":"0.00 %","fouledByOthers":2,"fouledOthers":0,"tacklesTotal":2,"interceptionsTotal":2,"shotsOnTarget":0,"shotsOffTarget":0,"shotsTotal":0,"shotsAccuracy":"0.00 %","penaltiesScored":0,"penaltiesMissed":0,"penaltiesTotal":0,"penaltiesAccuracy":"0.00 %","passesAccuracy":"92.00 %","passesSuccessful":23,"passesFailed":2,"passesTotal":25,"passesKey":0,"cardsRed":0,"cardsYellow":1,"cardsSecondYellow":1,"duelsTotal":4,"duelsWon":4,"duelsLost":0,"duelSuccessRate":"100.00 %","expectedAssists":0.02,"expectedGoals":null,"expectedGoalsOnTarget":null,"expectedGoalsOnTargetConceded":null,"expectedGoalsPrevented":null},"fullName":"Marc Aguado Pallares","logo":null},{"id":7620123,"name":"Adrià Pedrosa","matchRating":"7.01","shirtNumber":3,"position":"Defender","isCaptain":false,"minutesPlayed":26,"isSubstitute":true,"offsides":0,"statistics":{"goalsScored":0,"goalsSaved":0,"goalsConceded":0,"assists":0,"dribblesTotal":1,"dribblesSuccessful":0,"dribblesFailed":1,"dribbleSuccessRate":"0.00 %","fouledByOthers":1,"fouledOthers":1,"tacklesTotal":0,"interceptionsTotal":0,"shotsOnTarget":0,"shotsOffTarget":0,"shotsTotal":0,"shotsAccuracy":"0.00 %","penaltiesScored":0,"penaltiesMissed":0,"penaltiesTotal":0,"penaltiesAccuracy":"0.00 %","passesAccuracy":"66.67 %","passesSuccessful":6,"passesFailed":3,"passesTotal":9,"passesKey":3,"cardsRed":0,"cardsYellow":0,"cardsSecondYellow":0,"duelsTotal":3,"duelsWon":1,"duelsLost":2,"duelSuccessRate":"33.33 %","expectedAssists":0.44,"expectedGoals":null,"expectedGoalsOnTarget":null,"expectedGoalsOnTargetConceded":null,"expectedGoalsPrevented":null},"fullName":"Adrià Giner Pedrosa","logo":null},{"id":7569247,"name":"Rafa Mir","matchRating":"6.19","shirtNumber":10,"position":"Forward","isCaptain":false,"minutesPlayed":19,"isSubstitute":true,"offsides":0,"statistics":{"goalsScored":0,"goalsSaved":0,"goalsConceded":0,"assists":0,"dribblesTotal":0,"dribblesSuccessful":0,"dribblesFailed":0,"dribbleSuccessRate":"0.00 %","fouledByOthers":0,"fouledOthers":0,"tacklesTotal":0,"interceptionsTotal":0,"shotsOnTarget":0,"shotsOffTarget":0,"shotsTotal":0,"shotsAccuracy":"0.00 %","penaltiesScored":0,"penaltiesMissed":0,"penaltiesTotal":0,"penaltiesAccuracy":"0.00 %","passesAccuracy":"50.00 %","passesSuccessful":1,"passesFailed":1,"passesTotal":2,"passesKey":0,"cardsRed":0,"cardsYellow":0,"cardsSecondYellow":0,"duelsTotal":1,"duelsWon":0,"duelsLost":1,"duelSuccessRate":"0.00 %","expectedAssists":0,"expectedGoals":0.02,"expectedGoalsOnTarget":null,"expectedGoalsOnTargetConceded":null,"expectedGoalsPrevented":null},"fullName":"Rafael Mir Vicente","logo":null},{"id":45790969,"name":"Yago Santiago","matchRating":"6.50","shirtNumber":7,"position":"Forward","isCaptain":false,"minutesPlayed":18,"isSubstitute":true,"offsides":0,"statistics":{"goalsScored":0,"goalsSaved":0,"goalsConceded":0,"assists":0,"dribblesTotal":0,"dribblesSuccessful":0,"dribblesFailed":0,"dribbleSuccessRate":"0.00 %","fouledByOthers":0,"fouledOthers":0,"tacklesTotal":0,"interceptionsTotal":0,"shotsOnTarget":0,"shotsOffTarget":0,"shotsTotal":0,"shotsAccuracy":"0.00 %","penaltiesScored":0,"penaltiesMissed":0,"penaltiesTotal":0,"penaltiesAccuracy":"0.00 %","passesAccuracy":"78.57 %","passesSuccessful":11,"passesFailed":3,"passesTotal":14,"passesKey":0,"cardsRed":0,"cardsYellow":0,"cardsSecondYellow":0,"duelsTotal":0,"duelsWon":0,"duelsLost":0,"duelSuccessRate":"0.00 %","expectedAssists":0,"expectedGoals":null,"expectedGoalsOnTarget":null,"expectedGoalsOnTargetConceded":null,"expectedGoalsPrevented":null},"fullName":"Yago de Santiago Alonso","logo":null},{"id":1826860,"name":"Matías Dituro","matchRating":null,"shirtNumber":1,"position":"Goalkeeper","isCaptain":false,"minutesPlayed":0,"isSubstitute":true,"offsides":0,"statistics":{"goalsScored":0,"goalsSaved":0,"goalsConceded":0,"assists":0,"dribblesTotal":0,"dribblesSuccessful":0,"dribblesFailed":0,"dribbleSuccessRate":"0.00 %","fouledByOthers":0,"fouledOthers":0,"tacklesTotal":0,"interceptionsTotal":0,"shotsOnTarget":0,"shotsOffTarget":0,"shotsTotal":0,"shotsAccuracy":"0.00 %","penaltiesScored":0,"penaltiesMissed":0,"penaltiesTotal":0,"penaltiesAccuracy":"0.00 %","passesAccuracy":"0.00 %","passesSuccessful":0,"passesFailed":0,"passesTotal":0,"passesKey":0,"cardsRed":0,"cardsYellow":0,"cardsSecondYellow":0,"duelsTotal":0,"duelsWon":0,"duelsLost":0,"duelSuccessRate":"0.00 %","expectedAssists":0.02,"expectedGoals":null,"expectedGoalsOnTarget":null,"expectedGoalsOnTargetConceded":null,"expectedGoalsPrevented":null},"fullName":"Matías Ezequiel Dituro Curto","logo":null},{"id":50812398,"name":"Alejandro Iturbe","matchRating":null,"shirtNumber":45,"position":"Goalkeeper","isCaptain":false,"minutesPlayed":0,"isSubstitute":true,"offsides":0,"statistics":{"goalsScored":0,"goalsSaved":0,"goalsConceded":0,"assists":0,"dribblesTotal":0,"dribblesSuccessful":0,"dribblesFailed":0,"dribbleSuccessRate":"0.00 %","fouledByOthers":0,"fouledOthers":0,"tacklesTotal":0,"interceptionsTotal":0,"shotsOnTarget":0,"shotsOffTarget":0,"shotsTotal":0,"shotsAccuracy":"0.00 %","penaltiesScored":0,"penaltiesMissed":0,"penaltiesTotal":0,"penaltiesAccuracy":"0.00 %","passesAccuracy":"0.00 %","passesSuccessful":0,"passesFailed":0,"passesTotal":0,"passesKey":0,"cardsRed":0,"cardsYellow":0,"cardsSecondYellow":0,"duelsTotal":0,"duelsWon":0,"duelsLost":0,"duelSuccessRate":"0.00 %","expectedAssists":0.05,"expectedGoals":null,"expectedGoalsOnTarget":null,"expectedGoalsOnTargetConceded":null,"expectedGoalsPrevented":null},"fullName":"Alejandro Iturbe Encabo","logo":null},{"id":1408260,"name":"Bambo Diaby","matchRating":null,"shirtNumber":4,"position":"Defender","isCaptain":false,"minutesPlayed":0,"isSubstitute":true,"offsides":0,"statistics":{"goalsScored":0,"goalsSaved":0,"goalsConceded":0,"assists":0,"dribblesTotal":0,"dribblesSuccessful":0,"dribblesFailed":0,"dribbleSuccessRate":"0.00 %","fouledByOthers":0,"fouledOthers":0,"tacklesTotal":0,"interceptionsTotal":0,"shotsOnTarget":0,"shotsOffTarget":0,"shotsTotal":0,"shotsAccuracy":"0.00 %","penaltiesScored":0,"penaltiesMissed":0,"penaltiesTotal":0,"penaltiesAccuracy":"0.00 %","passesAccuracy":"0.00 %","passesSuccessful":0,"passesFailed":0,"passesTotal":0,"passesKey":0,"cardsRed":0,"cardsYellow":0,"cardsSecondYellow":0,"duelsTotal":0,"duelsWon":0,"duelsLost":0,"duelSuccessRate":"0.00 %","expectedAssists":null,"expectedGoals":null,"expectedGoalsOnTarget":null,"expectedGoalsOnTargetConceded":null,"expectedGoalsPrevented":null},"fullName":"Bambo Diaby Diaby","logo":null},{"id":30568580,"name":"John Donald","matchRating":null,"shirtNumber":18,"position":"Defender","isCaptain":false,"minutesPlayed":0,"isSubstitute":true,"offsides":0,"statistics":{"goalsScored":0,"goalsSaved":0,"goalsConceded":0,"assists":0,"dribblesTotal":0,"dribblesSuccessful":0,"dribblesFailed":0,"dribbleSuccessRate":"0.00 %","fouledByOthers":0,"fouledOthers":0,"tacklesTotal":0,"interceptionsTotal":0,"shotsOnTarget":0,"shotsOffTarget":0,"shotsTotal":0,"shotsAccuracy":"0.00 %","penaltiesScored":0,"penaltiesMissed":0,"penaltiesTotal":0,"penaltiesAccuracy":"0.00 %","passesAccuracy":"0.00 %","passesSuccessful":0,"passesFailed":0,"passesTotal":0,"passesKey":0,"cardsRed":0,"cardsYellow":0,"cardsSecondYellow":0,"duelsTotal":0,"duelsWon":0,"duelsLost":0,"duelSuccessRate":"0.00 %","expectedAssists":null,"expectedGoals":null,"expectedGoalsOnTarget":null,"expectedGoalsOnTargetConceded":null,"expectedGoalsPrevented":null},"fullName":"John Chetauya Nwankwo Donald Okeh","logo":null},{"id":7628012,"name":"Pedro Bigas","matchRating":null,"shirtNumber":6,"position":"Defender","isCaptain":false,"minutesPlayed":0,"isSubstitute":true,"offsides":0,"statistics":{"goalsScored":0,"goalsSaved":0,"goalsConceded":0,"assists":0,"dribblesTotal":0,"dribblesSuccessful":0,"dribblesFailed":0,"dribbleSuccessRate":"0.00 %","fouledByOthers":0,"fouledOthers":0,"tacklesTotal":0,"interceptionsTotal":0,"shotsOnTarget":0,"shotsOffTarget":0,"shotsTotal":0,"shotsAccuracy":"0.00 %","penaltiesScored":0,"penaltiesMissed":0,"penaltiesTotal":0,"penaltiesAccuracy":"0.00 %","passesAccuracy":"0.00 %","passesSuccessful":0,"passesFailed":0,"passesTotal":0,"passesKey":0,"cardsRed":0,"cardsYellow":0,"cardsSecondYellow":0,"duelsTotal":0,"duelsWon":0,"duelsLost":0,"duelSuccessRate":"0.00 %","expectedAssists":0.44,"expectedGoals":null,"expectedGoalsOnTarget":null,"expectedGoalsOnTargetConceded":null,"expectedGoalsPrevented":null},"fullName":"Pedro Bigas Rigo","logo":null},{"id":50126699,"name":"Federico Redondo","matchRating":null,"shirtNumber":5,"position":"Midfielder","isCaptain":false,"minutesPlayed":0,"isSubstitute":true,"offsides":0,"statistics":{"goalsScored":0,"goalsSaved":0,"goalsConceded":0,"assists":0,"dribblesTotal":0,"dribblesSuccessful":0,"dribblesFailed":0,"dribbleSuccessRate":"0.00 %","fouledByOthers":0,"fouledOthers":0,"tacklesTotal":0,"interceptionsTotal":0,"shotsOnTarget":0,"shotsOffTarget":0,"shotsTotal":0,"shotsAccuracy":"0.00 %","penaltiesScored":0,"penaltiesMissed":0,"penaltiesTotal":0,"penaltiesAccuracy":"0.00 %","passesAccuracy":"0.00 %","passesSuccessful":0,"passesFailed":0,"passesTotal":0,"passesKey":0,"cardsRed":0,"cardsYellow":0,"cardsSecondYellow":0,"duelsTotal":0,"duelsWon":0,"duelsLost":0,"duelSuccessRate":"0.00 %","expectedAssists":0.02,"expectedGoals":null,"expectedGoalsOnTarget":null,"expectedGoalsOnTargetConceded":null,"expectedGoalsPrevented":null},"fullName":"Federico Redondo Solari","logo":null},{"id":70726327,"name":"Adam Boayar","matchRating":null,"shirtNumber":32,"position":"Forward","isCaptain":false,"minutesPlayed":0,"isSubstitute":true,"offsides":0,"statistics":{"goalsScored":0,"goalsSaved":0,"goalsConceded":0,"assists":0,"dribblesTotal":0,"dribblesSuccessful":0,"dribblesFailed":0,"dribbleSuccessRate":"0.00 %","fouledByOthers":0,"fouledOthers":0,"tacklesTotal":0,"interceptionsTotal":0,"shotsOnTarget":0,"shotsOffTarget":0,"shotsTotal":0,"shotsAccuracy":"0.00 %","penaltiesScored":0,"penaltiesMissed":0,"penaltiesTotal":0,"penaltiesAccuracy":"0.00 %","passesAccuracy":"0.00 %","passesSuccessful":0,"passesFailed":0,"passesTotal":0,"passesKey":0,"cardsRed":0,"cardsYellow":0,"cardsSecondYellow":0,"duelsTotal":0,"duelsWon":0,"duelsLost":0,"duelSuccessRate":"0.00 %","expectedAssists":0.01,"expectedGoals":0.45,"expectedGoalsOnTarget":0.94,"expectedGoalsOnTargetConceded":null,"expectedGoalsPrevented":null},"fullName":"Adam Boayar Benaisa","logo":null}]}],"Count":2}}